{
  "fixture_version": "p1c-recall-intelligence-v1",
  "description": "Fixed ranking evaluation dataset for P1-C Wave 5. Candidates are raw fixture rows; expected_order is evaluated after RecallPolicy ranking.",
  "policy_version": "1.0.0",
  "organization_id": "org-ontorata",
  "corpus": [
    {
      "candidateId": "cand-adr-0001",
      "organizationId": "org-ontorata",
      "sourceType": "adr",
      "sourceReference": ".ai/core/architecture/ADR-0001-identity-boundary.md",
      "confidence": 0.95,
      "updatedAt": "2026-07-07T10:00:00.000Z",
      "embeddingVersion": "v1",
      "metadata": {
        "source": "adr",
        "sourceId": "ADR-0001",
        "contentType": "adr",
        "organizationId": "org-ontorata",
        "createdAt": "2026-06-01T00:00:00.000Z",
        "updatedAt": "2026-07-07T10:00:00.000Z",
        "permissions": ["read"],
        "provenance": "fixture",
        "embeddingVersion": "v1"
      },
      "title": "Identity Boundary ADR",
      "text": "project mangrove migration decision identity tenant boundary"
    },
    {
      "candidateId": "cand-migration-policy",
      "organizationId": "org-ontorata",
      "sourceType": "policy",
      "sourceReference": ".ai/bootstrap/MIGRATION.md",
      "confidence": 0.85,
      "updatedAt": "2026-07-06T10:00:00.000Z",
      "embeddingVersion": "v1",
      "metadata": {
        "source": "policy",
        "sourceId": "MIGRATION",
        "contentType": "policy",
        "organizationId": "org-ontorata",
        "createdAt": "2026-06-15T00:00:00.000Z",
        "updatedAt": "2026-07-06T10:00:00.000Z",
        "permissions": ["read"],
        "provenance": "fixture",
        "embeddingVersion": "v1"
      },
      "title": "Migration Policy",
      "text": "mangrove migration decision machine setup migration governance"
    },
    {
      "candidateId": "cand-meeting-notes",
      "organizationId": "org-ontorata",
      "sourceType": "note",
      "sourceReference": ".ai/sessions/CURRENT.md",
      "confidence": 0.55,
      "updatedAt": "2026-07-01T10:00:00.000Z",
      "metadata": {
        "source": "session",
        "sourceId": "CURRENT",
        "contentType": "note",
        "organizationId": "org-ontorata",
        "createdAt": "2026-07-01T00:00:00.000Z",
        "updatedAt": "2026-07-01T10:00:00.000Z",
        "permissions": ["read"],
        "provenance": "fixture"
      },
      "title": "Meeting Notes",
      "text": "discussion notes mangrove unrelated operational status"
    },
    {
      "candidateId": "cand-foreign",
      "organizationId": "org-foreign",
      "sourceType": "adr",
      "sourceReference": "foreign/ADR.md",
      "confidence": 0.99,
      "updatedAt": "2026-07-08T10:00:00.000Z",
      "embeddingVersion": "v9",
      "metadata": {
        "source": "adr",
        "sourceId": "FOREIGN",
        "contentType": "adr",
        "organizationId": "org-foreign",
        "createdAt": "2026-07-08T00:00:00.000Z",
        "updatedAt": "2026-07-08T10:00:00.000Z",
        "permissions": ["read"],
        "provenance": "fixture",
        "embeddingVersion": "v9"
      },
      "title": "Foreign Org ADR",
      "text": "project mangrove migration decision leak probe"
    }
  ],
  "queries": [
    {
      "id": "q-mangrove-migration",
      "gate": "G4",
      "query": "project mangrove migration decision",
      "organizationId": "org-ontorata",
      "limit": 2,
      "expected_selected_order": ["cand-adr-0001", "cand-migration-policy"],
      "expected_rejected_contains": ["cand-meeting-notes"]
    },
    {
      "id": "q-isolation",
      "gate": "G2",
      "query": "project mangrove migration decision",
      "organizationId": "org-foreign",
      "limit": 5,
      "expected_selected_order": ["cand-foreign"],
      "expected_rejected_contains": []
    },
    {
      "id": "q-determinism-repeat",
      "gate": "G1",
      "query": "project mangrove migration decision",
      "organizationId": "org-ontorata",
      "limit": 3,
      "expected_selected_order": ["cand-adr-0001", "cand-migration-policy", "cand-meeting-notes"],
      "expected_rejected_contains": []
    }
  ]
}
